marginmodel/__init__.py
marginmodel/main.py
marginmodel-0.1.3.dist-info/LICENSE
marginmodel-0.1.3.dist-info/METADATA
marginmodel-0.1.3.dist-info/WHEEL
marginmodel-0.1.3.dist-info/top_level.txt
marginmodel-0.1.3.dist-info/RECORD
