Metadata-Version: 2.1
Name: marginmodel
Version: 0.1.3
Summary: A margin model package
Author-email: Will Bradley <williambbradley@gmail.com>
License: Copyright (c) 2018 The Python Packaging Authority        
Project-URL: Homepage, https://github.com/wbbradley/marginmodel-pypi
Project-URL: Bug Tracker, https://github.com/wbbradley/marginmodel-pypi/issues
Classifier: Programming Language :: Python :: 3
Classifier: License :: OSI Approved :: MIT License
Classifier: Operating System :: OS Independent
Requires-Python: >=3.9
License-File: LICENSE
